CONTRIBUTING.md
LICENSE
MANIFEST.in
README.md
settings.ini
setup.py
fastinference2/__init__.py
fastinference2/_nbdev.py
fastinference2/class_confusion.py
fastinference2/onnx.py
fastinference2/soft_dependencies.py
fastinference2.egg-info/PKG-INFO
fastinference2.egg-info/SOURCES.txt
fastinference2.egg-info/dependency_links.txt
fastinference2.egg-info/not-zip-safe
fastinference2.egg-info/requires.txt
fastinference2.egg-info/top_level.txt
fastinference2/inference/__init__.py
fastinference2/inference/export.py
fastinference2/inference/inference.py
fastinference2/inference/text.py
fastinference2/tabular/__init__.py
fastinference2/tabular/core.py
fastinference2/tabular/interpretation.py
fastinference2/tabular/pd.py
fastinference2/tabular/waterfall.py
fastinference2/tabular/shap/__init__.py
fastinference2/tabular/shap/core.py
fastinference2/tabular/shap/interp.py