Metadata-Version: 2.1
Name: fastinference2
Version: 0.0.48
Summary: A collection of inference modules
Home-page: https://github.com/muellerzr/fastinference/tree/master/
Author: Zachary Mueller
Author-email: muellerzr@gmail.com
License: Apache Software License 2.0
Keywords: fastai pytorch fastai
Platform: UNKNOWN
Classifier: Development Status :: 3 - Alpha
Classifier: Intended Audience :: Developers
Classifier: License :: OSI Approved :: Apache Software License
Classifier: Natural Language :: English
Classifier: Programming Language :: Python :: 3.9
Requires-Python: >=3.9
Provides-Extra: onnx-gpu
Provides-Extra: onnx-cpu
Provides-Extra: interp
Provides-Extra: all
License-File: LICENSE
